watson/__init__.py
watson/common/__init__.py
watson/common/contextmanagers.py
watson/common/datastructures.py
watson/common/decorators.py
watson/common/imports.py
watson/common/json.py
watson/common/strings.py
watson/common/xml.py
watson_common-1.6.3.dist-info/AUTHORS
watson_common-1.6.3.dist-info/LICENSE
watson_common-1.6.3.dist-info/METADATA
watson_common-1.6.3.dist-info/WHEEL
watson_common-1.6.3.dist-info/top_level.txt
watson_common-1.6.3.dist-info/RECORD
