Metadata-Version: 2.1
Name: watson-common
Version: 1.6.3
Summary: Useful common utility functions and classes.
Home-page: http://github.com/watsonpy/watson-common
Author: Simon Coulton
Author-email: simon@bespohk.com
License: Copyright (c) Bespohk and individual contributors.
Provides-Extra: test
Requires-Dist: pytest ; extra == 'test'
Requires-Dist: pytest-cov ; extra == 'test'
Requires-Dist: coverage ; extra == 'test'
Requires-Dist: coveralls ; extra == 'test'
